startpypack/__init__.py
startpypack/addlines.py
startpypack/getlines.py
startpypack/makepackage.py
startpypack/mkdir.py
startpypack/mkfunc.py
startpypack/pkdirs.py
startpypack/pkmkfiles.py
startpypack/replacelines.py
startpypack/writefile.py
startpypack/files/data/MANIFEST.in
startpypack/files/data/README.rst
startpypack/files/data/__init__.py
startpypack/files/data/build.py
startpypack/files/data/data.txt
startpypack/files/data/exdocstring.py
startpypack/files/data/exfunc.py
startpypack/files/data/func1.py
startpypack/files/data/func2.py
startpypack/files/data/install.py
startpypack/files/data/setup.py
startpypack/files/data/upload.py
startpypack/files/docs/startpypackexample.py
startpypack-0.0.7.dist-info/DESCRIPTION.rst
startpypack-0.0.7.dist-info/METADATA
startpypack-0.0.7.dist-info/RECORD
startpypack-0.0.7.dist-info/WHEEL
startpypack-0.0.7.dist-info/metadata.json
startpypack-0.0.7.dist-info/top_level.txt
