Metadata-Version: 2.0
Name: startpypack
Version: 0.0.7
Summary: Initialize a new python package with python
Home-page: https://bitbucket.org/nrw16/startpypack
Author: Nick Wheeler
Author-email: nrw16@case.edu
License: GPL3
Platform: UNKNOWN
Requires-Dist: markdown
